alu.v
module alu (
    input  signed [7:0] a,
    input  signed [7:0] b,
    input  [2:0] op,
    output reg signed [7:0] y
);

always @(*) begin
    y   = 0;
    case (op)
        3'b000: y = a + b;                    //ADD
        3'b001: y = a - b;                    //SUB
        3'b010: y = a & b;                    //AND
        3'b011: y = a | b;                    //OR
        3'b100: y = (a & ~b) | (~a & b);      //XOR
        3'b101: y = 0;                        //Placeholder
        3'b110: y = 0;                        //Placeholder
        3'b111: y = 0;                        //Placeholder
    endcase
end

endmodule

alu.vcd
$version Generated by VerilatedVcd $end
$timescale 1ps $end
 $scope module TOP $end
  $var wire 8 # a [7:0] $end
  $var wire 8 $ b [7:0] $end
  $var wire 3 % op [2:0] $end
  $var wire 8 & y [7:0] $end
  $scope module alu $end
   $var wire 8 # a [7:0] $end
   $var wire 8 $ b [7:0] $end
   $var wire 3 % op [2:0] $end
   $var wire 8 & y [7:0] $end
  $upscope $end
 $upscope $end
$enddefinitions $end


#0
b10000000 #
b10000000 $
b000 %
b00000000 &
#1
b001 %
#2
b000 %
#3
b001 %
#4
#80
b10010000 $
b000 %
b00010000 &
#81
b001 %
b11110000 &
#82
b000 %
b00010000 &
#83
b001 %
b11110000 &
#84
#160
b10100000 $
b000 %
b00100000 &
#161
b001 %
b11100000 &
#162
b000 %
b00100000 &
#163
b001 %
b11100000 &
#164
#240
b10110000 $
b000 %
b00110000 &
#241
b001 %
b11010000 &
#242
b000 %
b00110000 &
#243
b001 %
b11010000 &
#244
#320
b11000000 $
b000 %
b01000000 &
#321
b001 %
b11000000 &
#322
b000 %
b01000000 &
#323
b001 %
b11000000 &
#324
#400
b11010000 $
b000 %
b01010000 &
#401
b001 %
b10110000 &
#402
b000 %
b01010000 &
#403
b001 %
b10110000 &
#404
#480
b11100000 $
b000 %
b01100000 &
#481
b001 %
b10100000 &
#482
b000 %
b01100000 &
#483
b001 %
b10100000 &
#484
#560
b11110000 $
b000 %
b01110000 &
#561
b001 %
b10010000 &
#562
b000 %
b01110000 &
#563
b001 %
b10010000 &
#564
#640
b00000000 $
b000 %
b10000000 &
#641
b001 %
#642
b000 %
#643
b001 %
#644
#720
b00010000 $
b000 %
b10010000 &
#721
b001 %
b01110000 &
#722
b000 %
b10010000 &
#723
b001 %
b01110000 &
#724
#800
b00100000 $
b000 %
b10100000 &
#801
b001 %
b01100000 &
#802
b000 %
b10100000 &
#803
b001 %
b01100000 &
#804
#880
b00110000 $
b000 %
b10110000 &
#881
b001 %
b01010000 &
#882
b000 %
b10110000 &
#883
b001 %
b01010000 &
#884
#960
b01000000 $
b000 %
b11000000 &
#961
b001 %
b01000000 &
#962
b000 %
b11000000 &
#963
b001 %
b01000000 &
#964
#1040
b01010000 $
b000 %
b11010000 &
#1041
b001 %
b00110000 &
#1042
b000 %
b11010000 &
#1043
b001 %
b00110000 &
#1044
#1120
b01100000 $
b000 %
b11100000 &
#1121
b001 %
b00100000 &
#1122
b000 %
b11100000 &
#1123
b001 %
b00100000 &
#1124
#1200
b01110000 $
b000 %
b11110000 &
#1201
b001 %
b00010000 &
#1202
b000 %
b11110000 &
#1203
b001 %
b00010000 &
#1204
#20480
b10010000 #
b10000000 $
b000 %
#20481
b001 %
#20482
b000 %
#20483
b001 %
#20484
#20560
b10010000 $
b000 %
b00100000 &
#20561
b001 %
b00000000 &
#20562
b000 %
b00100000 &
#20563
b001 %
b00000000 &
#20564
#20640
b10100000 $
b000 %
b00110000 &
#20641
b001 %
b11110000 &
#20642
b000 %
b00110000 &
#20643
b001 %
b11110000 &
#20644
#20720
b10110000 $
b000 %
b01000000 &
#20721
b001 %
b11100000 &
#20722
b000 %
b01000000 &
#20723
b001 %
b11100000 &
#20724
#20800
b11000000 $
b000 %
b01010000 &
#20801
b001 %
b11010000 &
#20802
b000 %
b01010000 &
#20803
b001 %
b11010000 &
#20804
#20880
b11010000 $
b000 %
b01100000 &
#20881
b001 %
b11000000 &
#20882
b000 %
b01100000 &
#20883
b001 %
b11000000 &
#20884
#20960
b11100000 $
b000 %
b01110000 &
#20961
b001 %
b10110000 &
#20962
b000 %
b01110000 &
#20963
b001 %
b10110000 &
#20964
#21040
b11110000 $
b000 %
b10000000 &
#21041
b001 %
b10100000 &
#21042
b000 %
b10000000 &
#21043
b001 %
b10100000 &
#21044
#21120
b00000000 $
b000 %
b10010000 &
#21121
b001 %
#21122
b000 %
#21123
b001 %
#21124
#21200
b00010000 $
b000 %
b10100000 &
#21201
b001 %
b10000000 &
#21202
b000 %
b10100000 &
#21203
b001 %
b10000000 &
#21204
#21280
b00100000 $
b000 %
b10110000 &
#21281
b001 %
b01110000 &
#21282
b000 %
b10110000 &
#21283
b001 %
b01110000 &
#21284
#21360
b00110000 $
b000 %
b11000000 &
#21361
b001 %
b01100000 &
#21362
b000 %
b11000000 &
#21363
b001 %
b01100000 &
#21364
#21440
b01000000 $
b000 %
b11010000 &
#21441
b001 %
b01010000 &
#21442
b000 %
b11010000 &
#21443
b001 %
b01010000 &
#21444
#21520
b01010000 $
b000 %
b11100000 &
#21521
b001 %
b01000000 &
#21522
b000 %
b11100000 &
#21523
b001 %
b01000000 &
#21524
#21600
b01100000 $
b000 %
b11110000 &
#21601
b001 %
b00110000 &
#21602
b000 %
b11110000 &
#21603
b001 %
b00110000 &
#21604
#21680
b01110000 $
b000 %
b00000000 &
#21681
b001 %
b00100000 &
#21682
b000 %
b00000000 &
#21683
b001 %
b00100000 &
#21684
#40960
b10100000 #
b10000000 $
b000 %
#40961
b001 %
#40962
b000 %
#40963
b001 %
#40964
#41040
b10010000 $
b000 %
b00110000 &
#41041
b001 %
b00010000 &
#41042
b000 %
b00110000 &
#41043
b001 %
b00010000 &
#41044
#41120
b10100000 $
b000 %
b01000000 &
#41121
b001 %
b00000000 &
#41122
b000 %
b01000000 &
#41123
b001 %
b00000000 &
#41124
#41200
b10110000 $
b000 %
b01010000 &
#41201
b001 %
b11110000 &
#41202
b000 %
b01010000 &
#41203
b001 %
b11110000 &
#41204
#41280
b11000000 $
b000 %
b01100000 &
#41281
b001 %
b11100000 &
#41282
b000 %
b01100000 &
#41283
b001 %
b11100000 &
#41284
#41360
b11010000 $
b000 %
b01110000 &
#41361
b001 %
b11010000 &
#41362
b000 %
b01110000 &
#41363
b001 %
b11010000 &
#41364
#41440
b11100000 $
b000 %
b10000000 &
#41441
b001 %
b11000000 &
#41442
b000 %
b10000000 &
#41443
b001 %
b11000000 &
#41444
#41520
b11110000 $
b000 %
b10010000 &
#41521
b001 %
b10110000 &
#41522
b000 %
b10010000 &
#41523
b001 %
b10110000 &
#41524
#41600
b00000000 $
b000 %
b10100000 &
#41601
b001 %
#41602
b000 %
#41603
b001 %
#41604
#41680
b00010000 $
b000 %
b10110000 &
#41681
b001 %
b10010000 &
#41682
b000 %
b10110000 &
#41683
b001 %
b10010000 &
#41684
#41760
b00100000 $
b000 %
b11000000 &
#41761
b001 %
b10000000 &
#41762
b000 %
b11000000 &
#41763
b001 %
b10000000 &
#41764
#41840
b00110000 $
b000 %
b11010000 &
#41841
b001 %
b01110000 &
#41842
b000 %
b11010000 &
#41843
b001 %
b01110000 &
#41844
#41920
b01000000 $
b000 %
b11100000 &
#41921
b001 %
b01100000 &
#41922
b000 %
b11100000 &
#41923
b001 %
b01100000 &
#41924
#42000
b01010000 $
b000 %
b11110000 &
#42001
b001 %
b01010000 &
#42002
b000 %
b11110000 &
#42003
b001 %
b01010000 &
#42004
#42080
b01100000 $
b000 %
b00000000 &
#42081
b001 %
b01000000 &
#42082
b000 %
b00000000 &
#42083
b001 %
b01000000 &
#42084
#42160
b01110000 $
b000 %
b00010000 &
#42161
b001 %
b00110000 &
#42162
b000 %
b00010000 &
#42163
b001 %
b00110000 &
#42164
#61440
b10110000 #
b10000000 $
b000 %
#61441
b001 %
#61442
b000 %
#61443
b001 %
#61444
#61520
b10010000 $
b000 %
b01000000 &
#61521
b001 %
b00100000 &
#61522
b000 %
b01000000 &
#61523
b001 %
b00100000 &
#61524
#61600
b10100000 $
b000 %
b01010000 &
#61601
b001 %
b00010000 &
#61602
b000 %
b01010000 &
#61603
b001 %
b00010000 &
#61604
#61680
b10110000 $
b000 %
b01100000 &
#61681
b001 %
b00000000 &
#61682
b000 %
b01100000 &
#61683
b001 %
b00000000 &
#61684
#61760
b11000000 $
b000 %
b01110000 &
#61761
b001 %
b11110000 &
#61762
b000 %
b01110000 &
#61763
b001 %
b11110000 &
#61764
#61840
b11010000 $
b000 %
b10000000 &
#61841
b001 %
b11100000 &
#61842
b000 %
b10000000 &
#61843
b001 %
b11100000 &
#61844
#61920
b11100000 $
b000 %
b10010000 &
#61921
b001 %
b11010000 &
#61922
b000 %
b10010000 &
#61923
b001 %
b11010000 &
#61924
#62000
b11110000 $
b000 %
b10100000 &
#62001
b001 %
b11000000 &
#62002
b000 %
b10100000 &
#62003
b001 %
b11000000 &
#62004
#62080
b00000000 $
b000 %
b10110000 &
#62081
b001 %
#62082
b000 %
#62083
b001 %
#62084
#62160
b00010000 $
b000 %
b11000000 &
#62161
b001 %
b10100000 &
#62162
b000 %
b11000000 &
#62163
b001 %
b10100000 &
#62164
#62240
b00100000 $
b000 %
b11010000 &
#62241
b001 %
b10010000 &
#62242
b000 %
b11010000 &
#62243
b001 %
b10010000 &
#62244
#62320
b00110000 $
b000 %
b11100000 &
#62321
b001 %
b10000000 &
#62322
b000 %
b11100000 &
#62323
b001 %
b10000000 &
#62324
#62400
b01000000 $
b000 %
b11110000 &
#62401
b001 %
b01110000 &
#62402
b000 %
b11110000 &
#62403
b001 %
b01110000 &
#62404
#62480
b01010000 $
b000 %
b00000000 &
#62481
b001 %
b01100000 &
#62482
b000 %
b00000000 &
#62483
b001 %
b01100000 &
#62484
#62560
b01100000 $
b000 %
b00010000 &
#62561
b001 %
b01010000 &
#62562
b000 %
b00010000 &
#62563
b001 %
b01010000 &
#62564
#62640
b01110000 $
b000 %
b00100000 &
#62641
b001 %
b01000000 &
#62642
b000 %
b00100000 &
#62643
b001 %
b01000000 &
#62644
#81920
b11000000 #
b10000000 $
b000 %
#81921
b001 %
#81922
b000 %
#81923
b001 %
#81924
#82000
b10010000 $
b000 %
b01010000 &
#82001
b001 %
b00110000 &
#82002
b000 %
b01010000 &
#82003
b001 %
b00110000 &
#82004
#82080
b10100000 $
b000 %
b01100000 &
#82081
b001 %
b00100000 &
#82082
b000 %
b01100000 &
#82083
b001 %
b00100000 &
#82084
#82160
b10110000 $
b000 %
b01110000 &
#82161
b001 %
b00010000 &
#82162
b000 %
b01110000 &
#82163
b001 %
b00010000 &
#82164
#82240
b11000000 $
b000 %
b10000000 &
#82241
b001 %
b00000000 &
#82242
b000 %
b10000000 &
#82243
b001 %
b00000000 &
#82244
#82320
b11010000 $
b000 %
b10010000 &
#82321
b001 %
b11110000 &
#82322
b000 %
b10010000 &
#82323
b001 %
b11110000 &
#82324
#82400
b11100000 $
b000 %
b10100000 &
#82401
b001 %
b11100000 &
#82402
b000 %
b10100000 &
#82403
b001 %
b11100000 &
#82404
#82480
b11110000 $
b000 %
b10110000 &
#82481
b001 %
b11010000 &
#82482
b000 %
b10110000 &
#82483
b001 %
b11010000 &
#82484
#82560
b00000000 $
b000 %
b11000000 &
#82561
b001 %
#82562
b000 %
#82563
b001 %
#82564
#82640
b00010000 $
b000 %
b11010000 &
#82641
b001 %
b10110000 &
#82642
b000 %
b11010000 &
#82643
b001 %
b10110000 &
#82644
#82720
b00100000 $
b000 %
b11100000 &
#82721
b001 %
b10100000 &
#82722
b000 %
b11100000 &
#82723
b001 %
b10100000 &
#82724
#82800
b00110000 $
b000 %
b11110000 &
#82801
b001 %
b10010000 &
#82802
b000 %
b11110000 &
#82803
b001 %
b10010000 &
#82804
#82880
b01000000 $
b000 %
b00000000 &
#82881
b001 %
b10000000 &
#82882
b000 %
b00000000 &
#82883
b001 %
b10000000 &
#82884
#82960
b01010000 $
b000 %
b00010000 &
#82961
b001 %
b01110000 &
#82962
b000 %
b00010000 &
#82963
b001 %
b01110000 &
#82964
#83040
b01100000 $
b000 %
b00100000 &
#83041
b001 %
b01100000 &
#83042
b000 %
b00100000 &
#83043
b001 %
b01100000 &
#83044
#83120
b01110000 $
b000 %
b00110000 &
#83121
b001 %
b01010000 &
#83122
b000 %
b00110000 &
#83123
b001 %
b01010000 &
#83124
#102400
b11010000 #
b10000000 $
b000 %
#102401
b001 %
#102402
b000 %
#102403
b001 %
#102404
#102480
b10010000 $
b000 %
b01100000 &
#102481
b001 %
b01000000 &
#102482
b000 %
b01100000 &
#102483
b001 %
b01000000 &
#102484
#102560
b10100000 $
b000 %
b01110000 &
#102561
b001 %
b00110000 &
#102562
b000 %
b01110000 &
#102563
b001 %
b00110000 &
#102564
#102640
b10110000 $
b000 %
b10000000 &
#102641
b001 %
b00100000 &
#102642
b000 %
b10000000 &
#102643
b001 %
b00100000 &
#102644
#102720
b11000000 $
b000 %
b10010000 &
#102721
b001 %
b00010000 &
#102722
b000 %
b10010000 &
#102723
b001 %
b00010000 &
#102724
#102800
b11010000 $
b000 %
b10100000 &
#102801
b001 %
b00000000 &
#102802
b000 %
b10100000 &
#102803
b001 %
b00000000 &
#102804
#102880
b11100000 $
b000 %
b10110000 &
#102881
b001 %
b11110000 &
#102882
b000 %
b10110000 &
#102883
b001 %
b11110000 &
#102884
#102960
b11110000 $
b000 %
b11000000 &
#102961
b001 %
b11100000 &
#102962
b000 %
b11000000 &
#102963
b001 %
b11100000 &
#102964
#103040
b00000000 $
b000 %
b11010000 &
#103041
b001 %
#103042
b000 %
#103043
b001 %
#103044
#103120
b00010000 $
b000 %
b11100000 &
#103121
b001 %
b11000000 &
#103122
b000 %
b11100000 &
#103123
b001 %
b11000000 &
#103124
#103200
b00100000 $
b000 %
b11110000 &
#103201
b001 %
b10110000 &
#103202
b000 %
b11110000 &
#103203
b001 %
b10110000 &
#103204
#103280
b00110000 $
b000 %
b00000000 &
#103281
b001 %
b10100000 &
#103282
b000 %
b00000000 &
#103283
b001 %
b10100000 &
#103284
#103360
b01000000 $
b000 %
b00010000 &
#103361
b001 %
b10010000 &
#103362
b000 %
b00010000 &
#103363
b001 %
b10010000 &
#103364
#103440
b01010000 $
b000 %
b00100000 &
#103441
b001 %
b10000000 &
#103442
b000 %
b00100000 &
#103443
b001 %
b10000000 &
#103444
#103520
b01100000 $
b000 %
b00110000 &
#103521
b001 %
b01110000 &
#103522
b000 %
b00110000 &
#103523
b001 %
b01110000 &
#103524
#103600
b01110000 $
b000 %
b01000000 &
#103601
b001 %
b01100000 &
#103602
b000 %
b01000000 &
#103603
b001 %
b01100000 &
#103604
#122880
b11100000 #
b10000000 $
b000 %
#122881
b001 %
#122882
b000 %
#122883
b001 %
#122884
#122960
b10010000 $
b000 %
b01110000 &
#122961
b001 %
b01010000 &
#122962
b000 %
b01110000 &
#122963
b001 %
b01010000 &
#122964
#123040
b10100000 $
b000 %
b10000000 &
#123041
b001 %
b01000000 &
#123042
b000 %
b10000000 &
#123043
b001 %
b01000000 &
#123044
#123120
b10110000 $
b000 %
b10010000 &
#123121
b001 %
b00110000 &
#123122
b000 %
b10010000 &
#123123
b001 %
b00110000 &
#123124
#123200
b11000000 $
b000 %
b10100000 &
#123201
b001 %
b00100000 &
#123202
b000 %
b10100000 &
#123203
b001 %
b00100000 &
#123204
#123280
b11010000 $
b000 %
b10110000 &
#123281
b001 %
b00010000 &
#123282
b000 %
b10110000 &
#123283
b001 %
b00010000 &
#123284
#123360
b11100000 $
b000 %
b11000000 &
#123361
b001 %
b00000000 &
#123362
b000 %
b11000000 &
#123363
b001 %
b00000000 &
#123364
#123440
b11110000 $
b000 %
b11010000 &
#123441
b001 %
b11110000 &
#123442
b000 %
b11010000 &
#123443
b001 %
b11110000 &
#123444
#123520
b00000000 $
b000 %
b11100000 &
#123521
b001 %
#123522
b000 %
#123523
b001 %
#123524
#123600
b00010000 $
b000 %
b11110000 &
#123601
b001 %
b11010000 &
#123602
b000 %
b11110000 &
#123603
b001 %
b11010000 &
#123604
#123680
b00100000 $
b000 %
b00000000 &
#123681
b001 %
b11000000 &
#123682
b000 %
b00000000 &
#123683
b001 %
b11000000 &
#123684
#123760
b00110000 $
b000 %
b00010000 &
#123761
b001 %
b10110000 &
#123762
b000 %
b00010000 &
#123763
b001 %
b10110000 &
#123764
#123840
b01000000 $
b000 %
b00100000 &
#123841
b001 %
b10100000 &
#123842
b000 %
b00100000 &
#123843
b001 %
b10100000 &
#123844
#123920
b01010000 $
b000 %
b00110000 &
#123921
b001 %
b10010000 &
#123922
b000 %
b00110000 &
#123923
b001 %
b10010000 &
#123924
#124000
b01100000 $
b000 %
b01000000 &
#124001
b001 %
b10000000 &
#124002
b000 %
b01000000 &
#124003
b001 %
b10000000 &
#124004
#124080
b01110000 $
b000 %
b01010000 &
#124081
b001 %
b01110000 &
#124082
b000 %
b01010000 &
#124083
b001 %
b01110000 &
#124084
#143360
b11110000 #
b10000000 $
b000 %
#143361
b001 %
#143362
b000 %
#143363
b001 %
#143364
#143440
b10010000 $
b000 %
b10000000 &
#143441
b001 %
b01100000 &
#143442
b000 %
b10000000 &
#143443
b001 %
b01100000 &
#143444
#143520
b10100000 $
b000 %
b10010000 &
#143521
b001 %
b01010000 &
#143522
b000 %
b10010000 &
#143523
b001 %
b01010000 &
#143524
#143600
b10110000 $
b000 %
b10100000 &
#143601
b001 %
b01000000 &
#143602
b000 %
b10100000 &
#143603
b001 %
b01000000 &
#143604
#143680
b11000000 $
b000 %
b10110000 &
#143681
b001 %
b00110000 &
#143682
b000 %
b10110000 &
#143683
b001 %
b00110000 &
#143684
#143760
b11010000 $
b000 %
b11000000 &
#143761
b001 %
b00100000 &
#143762
b000 %
b11000000 &
#143763
b001 %
b00100000 &
#143764
#143840
b11100000 $
b000 %
b11010000 &
#143841
b001 %
b00010000 &
#143842
b000 %
b11010000 &
#143843
b001 %
b00010000 &
#143844
#143920
b11110000 $
b000 %
b11100000 &
#143921
b001 %
b00000000 &
#143922
b000 %
b11100000 &
#143923
b001 %
b00000000 &
#143924
#144000
b00000000 $
b000 %
b11110000 &
#144001
b001 %
#144002
b000 %
#144003
b001 %
#144004
#144080
b00010000 $
b000 %
b00000000 &
#144081
b001 %
b11100000 &
#144082
b000 %
b00000000 &
#144083
b001 %
b11100000 &
#144084
#144160
b00100000 $
b000 %
b00010000 &
#144161
b001 %
b11010000 &
#144162
b000 %
b00010000 &
#144163
b001 %
b11010000 &
#144164
#144240
b00110000 $
b000 %
b00100000 &
#144241
b001 %
b11000000 &
#144242
b000 %
b00100000 &
#144243
b001 %
b11000000 &
#144244
#144320
b01000000 $
b000 %
b00110000 &
#144321
b001 %
b10110000 &
#144322
b000 %
b00110000 &
#144323
b001 %
b10110000 &
#144324
#144400
b01010000 $
b000 %
b01000000 &
#144401
b001 %
b10100000 &
#144402
b000 %
b01000000 &
#144403
b001 %
b10100000 &
#144404
#144480
b01100000 $
b000 %
b01010000 &
#144481
b001 %
b10010000 &
#144482
b000 %
b01010000 &
#144483
b001 %
b10010000 &
#144484
#144560
b01110000 $
b000 %
b01100000 &
#144561
b001 %
b10000000 &
#144562
b000 %
b01100000 &
#144563
b001 %
b10000000 &
#144564
#163840
b00000000 #
b10000000 $
b000 %
#163841
b001 %
#163842
b000 %
#163843
b001 %
#163844
#163920
b10010000 $
b000 %
b10010000 &
#163921
b001 %
b01110000 &
#163922
b000 %
b10010000 &
#163923
b001 %
b01110000 &
#163924
#164000
b10100000 $
b000 %
b10100000 &
#164001
b001 %
b01100000 &
#164002
b000 %
b10100000 &
#164003
b001 %
b01100000 &
#164004
#164080
b10110000 $
b000 %
b10110000 &
#164081
b001 %
b01010000 &
#164082
b000 %
b10110000 &
#164083
b001 %
b01010000 &
#164084
#164160
b11000000 $
b000 %
b11000000 &
#164161
b001 %
b01000000 &
#164162
b000 %
b11000000 &
#164163
b001 %
b01000000 &
#164164
#164240
b11010000 $
b000 %
b11010000 &
#164241
b001 %
b00110000 &
#164242
b000 %
b11010000 &
#164243
b001 %
b00110000 &
#164244
#164320
b11100000 $
b000 %
b11100000 &
#164321
b001 %
b00100000 &
#164322
b000 %
b11100000 &
#164323
b001 %
b00100000 &
#164324
#164400
b11110000 $
b000 %
b11110000 &
#164401
b001 %
b00010000 &
#164402
b000 %
b11110000 &
#164403
b001 %
b00010000 &
#164404
#164480
b00000000 $
b000 %
b00000000 &
#164481
b001 %
#164482
b000 %
#164483
b001 %
#164484
#164560
b00010000 $
b000 %
b00010000 &
#164561
b001 %
b11110000 &
#164562
b000 %
b00010000 &
#164563
b001 %
b11110000 &
#164564
#164640
b00100000 $
b000 %
b00100000 &
#164641
b001 %
b11100000 &
#164642
b000 %
b00100000 &
#164643
b001 %
b11100000 &
#164644
#164720
b00110000 $
b000 %
b00110000 &
#164721
b001 %
b11010000 &
#164722
b000 %
b00110000 &
#164723
b001 %
b11010000 &
#164724
#164800
b01000000 $
b000 %
b01000000 &
#164801
b001 %
b11000000 &
#164802
b000 %
b01000000 &
#164803
b001 %
b11000000 &
#164804
#164880
b01010000 $
b000 %
b01010000 &
#164881
b001 %
b10110000 &
#164882
b000 %
b01010000 &
#164883
b001 %
b10110000 &
#164884
#164960
b01100000 $
b000 %
b01100000 &
#164961
b001 %
b10100000 &
#164962
b000 %
b01100000 &
#164963
b001 %
b10100000 &
#164964
#165040
b01110000 $
b000 %
b01110000 &
#165041
b001 %
b10010000 &
#165042
b000 %
b01110000 &
#165043
b001 %
b10010000 &
#165044
#184320
b00010000 #
b10000000 $
b000 %
#184321
b001 %
#184322
b000 %
#184323
b001 %
#184324
#184400
b10010000 $
b000 %
b10100000 &
#184401
b001 %
b10000000 &
#184402
b000 %
b10100000 &
#184403
b001 %
b10000000 &
#184404
#184480
b10100000 $
b000 %
b10110000 &
#184481
b001 %
b01110000 &
#184482
b000 %
b10110000 &
#184483
b001 %
b01110000 &
#184484
#184560
b10110000 $
b000 %
b11000000 &
#184561
b001 %
b01100000 &
#184562
b000 %
b11000000 &
#184563
b001 %
b01100000 &
#184564
#184640
b11000000 $
b000 %
b11010000 &
#184641
b001 %
b01010000 &
#184642
b000 %
b11010000 &
#184643
b001 %
b01010000 &
#184644
#184720
b11010000 $
b000 %
b11100000 &
#184721
b001 %
b01000000 &
#184722
b000 %
b11100000 &
#184723
b001 %
b01000000 &
#184724
#184800
b11100000 $
b000 %
b11110000 &
#184801
b001 %
b00110000 &
#184802
b000 %
b11110000 &
#184803
b001 %
b00110000 &
#184804
#184880
b11110000 $
b000 %
b00000000 &
#184881
b001 %
b00100000 &
#184882
b000 %
b00000000 &
#184883
b001 %
b00100000 &
#184884
#184960
b00000000 $
b000 %
b00010000 &
#184961
b001 %
#184962
b000 %
#184963
b001 %
#184964
#185040
b00010000 $
b000 %
b00100000 &
#185041
b001 %
b00000000 &
#185042
b000 %
b00100000 &
#185043
b001 %
b00000000 &
#185044
#185120
b00100000 $
b000 %
b00110000 &
#185121
b001 %
b11110000 &
#185122
b000 %
b00110000 &
#185123
b001 %
b11110000 &
#185124
#185200
b00110000 $
b000 %
b01000000 &
#185201
b001 %
b11100000 &
#185202
b000 %
b01000000 &
#185203
b001 %
b11100000 &
#185204
#185280
b01000000 $
b000 %
b01010000 &
#185281
b001 %
b11010000 &
#185282
b000 %
b01010000 &
#185283
b001 %
b11010000 &
#185284
#185360
b01010000 $
b000 %
b01100000 &
#185361
b001 %
b11000000 &
#185362
b000 %
b01100000 &
#185363
b001 %
b11000000 &
#185364
#185440
b01100000 $
b000 %
b01110000 &
#185441
b001 %
b10110000 &
#185442
b000 %
b01110000 &
#185443
b001 %
b10110000 &
#185444
#185520
b01110000 $
b000 %
b10000000 &
#185521
b001 %
b10100000 &
#185522
b000 %
b10000000 &
#185523
b001 %
b10100000 &
#185524
#204800
b00100000 #
b10000000 $
b000 %
#204801
b001 %
#204802
b000 %
#204803
b001 %
#204804
#204880
b10010000 $
b000 %
b10110000 &
#204881
b001 %
b10010000 &
#204882
b000 %
b10110000 &
#204883
b001 %
b10010000 &
#204884
#204960
b10100000 $
b000 %
b11000000 &
#204961
b001 %
b10000000 &
#204962
b000 %
b11000000 &
#204963
b001 %
b10000000 &
#204964
#205040
b10110000 $
b000 %
b11010000 &
#205041
b001 %
b01110000 &
#205042
b000 %
b11010000 &
#205043
b001 %
b01110000 &
#205044
#205120
b11000000 $
b000 %
b11100000 &
#205121
b001 %
b01100000 &
#205122
b000 %
b11100000 &
#205123
b001 %
b01100000 &
#205124
#205200
b11010000 $
b000 %
b11110000 &
#205201
b001 %
b01010000 &
#205202
b000 %
b11110000 &
#205203
b001 %
b01010000 &
#205204
#205280
b11100000 $
b000 %
b00000000 &
#205281
b001 %
b01000000 &
#205282
b000 %
b00000000 &
#205283
b001 %
b01000000 &
#205284
#205360
b11110000 $
b000 %
b00010000 &
#205361
b001 %
b00110000 &
#205362
b000 %
b00010000 &
#205363
b001 %
b00110000 &
#205364
#205440
b00000000 $
b000 %
b00100000 &
#205441
b001 %
#205442
b000 %
#205443
b001 %
#205444
#205520
b00010000 $
b000 %
b00110000 &
#205521
b001 %
b00010000 &
#205522
b000 %
b00110000 &
#205523
b001 %
b00010000 &
#205524
#205600
b00100000 $
b000 %
b01000000 &
#205601
b001 %
b00000000 &
#205602
b000 %
b01000000 &
#205603
b001 %
b00000000 &
#205604
#205680
b00110000 $
b000 %
b01010000 &
#205681
b001 %
b11110000 &
#205682
b000 %
b01010000 &
#205683
b001 %
b11110000 &
#205684
#205760
b01000000 $
b000 %
b01100000 &
#205761
b001 %
b11100000 &
#205762
b000 %
b01100000 &
#205763
b001 %
b11100000 &
#205764
#205840
b01010000 $
b000 %
b01110000 &
#205841
b001 %
b11010000 &
#205842
b000 %
b01110000 &
#205843
b001 %
b11010000 &
#205844
#205920
b01100000 $
b000 %
b10000000 &
#205921
b001 %
b11000000 &
#205922
b000 %
b10000000 &
#205923
b001 %
b11000000 &
#205924
#206000
b01110000 $
b000 %
b10010000 &
#206001
b001 %
b10110000 &
#206002
b000 %
b10010000 &
#206003
b001 %
b10110000 &
#206004
#225280
b00110000 #
b10000000 $
b000 %
#225281
b001 %
#225282
b000 %
#225283
b001 %
#225284
#225360
b10010000 $
b000 %
b11000000 &
#225361
b001 %
b10100000 &
#225362
b000 %
b11000000 &
#225363
b001 %
b10100000 &
#225364
#225440
b10100000 $
b000 %
b11010000 &
#225441
b001 %
b10010000 &
#225442
b000 %
b11010000 &
#225443
b001 %
b10010000 &
#225444
#225520
b10110000 $
b000 %
b11100000 &
#225521
b001 %
b10000000 &
#225522
b000 %
b11100000 &
#225523
b001 %
b10000000 &
#225524
#225600
b11000000 $
b000 %
b11110000 &
#225601
b001 %
b01110000 &
#225602
b000 %
b11110000 &
#225603
b001 %
b01110000 &
#225604
#225680
b11010000 $
b000 %
b00000000 &
#225681
b001 %
b01100000 &
#225682
b000 %
b00000000 &
#225683
b001 %
b01100000 &
#225684
#225760
b11100000 $
b000 %
b00010000 &
#225761
b001 %
b01010000 &
#225762
b000 %
b00010000 &
#225763
b001 %
b01010000 &
#225764
#225840
b11110000 $
b000 %
b00100000 &
#225841
b001 %
b01000000 &
#225842
b000 %
b00100000 &
#225843
b001 %
b01000000 &
#225844
#225920
b00000000 $
b000 %
b00110000 &
#225921
b001 %
#225922
b000 %
#225923
b001 %
#225924
#226000
b00010000 $
b000 %
b01000000 &
#226001
b001 %
b00100000 &
#226002
b000 %
b01000000 &
#226003
b001 %
b00100000 &
#226004
#226080
b00100000 $
b000 %
b01010000 &
#226081
b001 %
b00010000 &
#226082
b000 %
b01010000 &
#226083
b001 %
b00010000 &
#226084
#226160
b00110000 $
b000 %
b01100000 &
#226161
b001 %
b00000000 &
#226162
b000 %
b01100000 &
#226163
b001 %
b00000000 &
#226164
#226240
b01000000 $
b000 %
b01110000 &
#226241
b001 %
b11110000 &
#226242
b000 %
b01110000 &
#226243
b001 %
b11110000 &
#226244
#226320
b01010000 $
b000 %
b10000000 &
#226321
b001 %
b11100000 &
#226322
b000 %
b10000000 &
#226323
b001 %
b11100000 &
#226324
#226400
b01100000 $
b000 %
b10010000 &
#226401
b001 %
b11010000 &
#226402
b000 %
b10010000 &
#226403
b001 %
b11010000 &
#226404
#226480
b01110000 $
b000 %
b10100000 &
#226481
b001 %
b11000000 &
#226482
b000 %
b10100000 &
#226483
b001 %
b11000000 &
#226484
#245760
b01000000 #
b10000000 $
b000 %
#245761
b001 %
#245762
b000 %
#245763
b001 %
#245764
#245840
b10010000 $
b000 %
b11010000 &
#245841
b001 %
b10110000 &
#245842
b000 %
b11010000 &
#245843
b001 %
b10110000 &
#245844
#245920
b10100000 $
b000 %
b11100000 &
#245921
b001 %
b10100000 &
#245922
b000 %
b11100000 &
#245923
b001 %
b10100000 &
#245924
#246000
b10110000 $
b000 %
b11110000 &
#246001
b001 %
b10010000 &
#246002
b000 %
b11110000 &
#246003
b001 %
b10010000 &
#246004
#246080
b11000000 $
b000 %
b00000000 &
#246081
b001 %
b10000000 &
#246082
b000 %
b00000000 &
#246083
b001 %
b10000000 &
#246084
#246160
b11010000 $
b000 %
b00010000 &
#246161
b001 %
b01110000 &
#246162
b000 %
b00010000 &
#246163
b001 %
b01110000 &
#246164
#246240
b11100000 $
b000 %
b00100000 &
#246241
b001 %
b01100000 &
#246242
b000 %
b00100000 &
#246243
b001 %
b01100000 &
#246244
#246320
b11110000 $
b000 %
b00110000 &
#246321
b001 %
b01010000 &
#246322
b000 %
b00110000 &
#246323
b001 %
b01010000 &
#246324
#246400
b00000000 $
b000 %
b01000000 &
#246401
b001 %
#246402
b000 %
#246403
b001 %
#246404
#246480
b00010000 $
b000 %
b01010000 &
#246481
b001 %
b00110000 &
